{"name":null,"assets":"aoy4:pathy29:assets%2Fdata%2Fc1Opening.txty4:sizei1036y4:typey4:TEXTy2:idR1y7:preloadtgoR0y34:assets%2Fdata%2Fdata-goes-here.txtR2zR3R4R5R7R6tgoR2i7664060R3y4:FONTy9:classNamey29:__ASSET__assets_data_font_ttfR5y24:assets%2Fdata%2Ffont.ttfR6tgoR0y33:assets%2Fdata%2FforestMission.txtR2i373R3R4R5R12R6tgoR0y31:assets%2Fdata%2FlakeTalking.txtR2i62R3R4R5R13R6tgoR0y29:assets%2Fdata%2FminerMap.jsonR2i88679R3R4R5R14R6tgoR0y32:assets%2Fdata%2FminerSpartan.txtR2i503R3R4R5R15R6tgoR0y31:assets%2Fdata%2FmingTalking.txtR2i690R3R4R5R16R6tgoR0y32:assets%2Fdata%2FmonumentMap.jsonR2i94995R3R4R5R17R6tgoR0y27:assets%2Fdata%2Fscript.docxR2i27800R3y6:BINARYR5R18R6tgoR0y28:assets%2Fdata%2FshopTalk.txtR2i181R3R4R5R20R6tgoR2i3381148R3R8R9y31:__ASSET__assets_data_silver_ttfR5y26:assets%2Fdata%2Fsilver.ttfR6tgoR0y28:assets%2Fdata%2FtestMap.ogmoR2i73340R3R4R5R23R6tgoR0y25:assets%2Fimages%2Fape.pngR2i1056R3y5:IMAGER5R24R6tgoR0y28:assets%2Fimages%2FapeNew.pngR2i6020R3R25R5R26R6tgoR0y29:assets%2Fimages%2FbagDeal.pngR2i3155R3R25R5R27R6tgoR0y29:assets%2Fimages%2FbagItem.pngR2i3068R3R25R5R28R6tgoR0y28:assets%2Fimages%2Fbanana.pngR2i798R3R25R5R29R6tgoR0y32:assets%2Fimages%2FbananaIcon.pngR2i348R3R25R5R30R6tgoR0y35:assets%2Fimages%2FbananaToStone.gifR2i8114602R3R25R5R31R6tgoR0y30:assets%2Fimages%2FboxEmpty.pngR2i699R3R25R5R32R6tgoR0y29:assets%2Fimages%2FboxFull.pngR2i1189R3R25R5R33R6tgoR0y28:assets%2Fimages%2Fbubble.pngR2i194R3R25R5R34R6tgoR0y32:assets%2Fimages%2FcloudMiner.pngR2i647R3R25R5R35R6tgoR0y38:assets%2Fimages%2FcombatBackground.pngR2i24748R3R25R5R36R6tgoR0y28:assets%2Fimages%2FdiaApe.pngR2i2816R3R25R5R37R6tgoR0y29:assets%2Fimages%2FdiaDoge.pngR2i3037R3R25R5R38R6tgoR0y29:assets%2Fimages%2FdiaLake.pngR2i1625R3R25R5R39R6tgoR0y29:assets%2Fimages%2FdiaMing.pngR2i2425R3R25R5R40R6tgoR0y29:assets%2Fimages%2FdiaNull.pngR2i1225R3R25R5R41R6tgoR0y31:assets%2Fimages%2FdiaSbBlue.pngR2i2757R3R25R5R42R6tgoR0y32:assets%2Fimages%2FdiaSbGreen.pngR2i2821R3R25R5R43R6tgoR0y30:assets%2Fimages%2FdiaSbRed.pngR2i2766R3R25R5R44R6tgoR0y32:assets%2Fimages%2FdiaSpartan.pngR2i3368R3R25R5R45R6tgoR0y26:assets%2Fimages%2Fdoge.pngR2i738R3R25R5R46R6tgoR0y36:assets%2Fimages%2Fimages-go-here.txtR2zR3R4R5R47R6tgoR0y31:assets%2Fimages%2FmenuAbout.pngR2i4592R3R25R5R48R6tgoR0y30:assets%2Fimages%2FmenuMain.pngR2i12638R3R25R5R49R6tgoR0y31:assets%2Fimages%2FminerDoor.pngR2i1480R3R25R5R50R6tgoR0y30:assets%2Fimages%2Fmonument.pngR2i1502R3R25R5R51R6tgoR0y29:assets%2Fimages%2FmtSmall.pngR2i29697R3R25R5R52R6tgoR0y25:assets%2Fimages%2Fnft.pngR2i488R3R25R5R53R6tgoR0y38:assets%2Fimages%2FopeningAnimation.pngR2i725469R3R25R5R54R6tgoR0y29:assets%2Fimages%2Fpointer.pngR2i169R3R25R5R55R6tgoR0y27:assets%2Fimages%2Fponzi.pngR2i611R3R25R5R56R6tgoR0y30:assets%2Fimages%2FponziBad.pngR2i605R3R25R5R57R6tgoR0y31:assets%2Fimages%2FponziFire.pngR2i5674R3R25R5R58R6tgoR0y31:assets%2Fimages%2FsaveStone.pngR2i2048R3R25R5R59R6tgoR0y28:assets%2Fimages%2FsbBlue.pngR2i797R3R25R5R60R6tgoR0y29:assets%2Fimages%2FsbGreen.pngR2i803R3R25R5R61R6tgoR0y27:assets%2Fimages%2FsbRed.pngR2i770R3R25R5R62R6tgoR0y29:assets%2Fimages%2FsbWhite.pngR2i579R3R25R5R63R6tgoR0y31:assets%2Fimages%2FshibaCoin.pngR2i615R3R25R5R64R6tgoR0y32:assets%2Fimages%2Fshopkeeper.pngR2i8527R3R25R5R65R6tgoR0y28:assets%2Fimages%2FshopUi.pngR2i1643R3R25R5R66R6tgoR0y29:assets%2Fimages%2Fspartan.pngR2i963R3R25R5R67R6tgoR0y27:assets%2Fimages%2Fstone.pngR2i351R3R25R5R68R6tgoR0y36:assets%2Fmusic%2Fmusic-goes-here.txtR2zR3R4R5R69R6tgoR2i2924R3y5:MUSICR5y26:assets%2Fsounds%2Fbeep.mp3y9:pathGroupaR71hR6tgoR2i23978R3y5:SOUNDR5y26:assets%2Fsounds%2Fcoin.wavR72aR74hR6tgoR2i39300R3R73R5y28:assets%2Fsounds%2Fcombat.wavR72aR75hR6tgoR2i34298R3R73R5y26:assets%2Fsounds%2Ffled.wavR72aR76hR6tgoR2i10188R3R73R5y31:assets%2Fsounds%2FgetBanana.wavR72aR77hR6tgoR2i20012R3R73R5y26:assets%2Fsounds%2Fhurt.wavR72aR78hR6tgoR2i33516R3R73R5y26:assets%2Fsounds%2Flose.wavR72aR79hR6tgoR2i24158R3R73R5y26:assets%2Fsounds%2Fmiss.wavR72aR80hR6tgoR2i10518R3R73R5y28:assets%2Fsounds%2Fselect.wavR72aR81hR6tgoR0y36:assets%2Fsounds%2Fsounds-go-here.txtR2zR3R4R5R82R6tgoR2i10188R3R73R5y28:assets%2Fsounds%2Fspeech.wavR72aR83hR6tgoR2i10188R3R73R5y26:assets%2Fsounds%2Fstep.wavR72aR84hR6tgoR2i54320R3R73R5y25:assets%2Fsounds%2Fwin.wavR72aR85hR6tgoR2i2114R3R70R5y26:flixel%2Fsounds%2Fbeep.mp3R72aR86y26:flixel%2Fsounds%2Fbeep.ogghR6tgoR2i39706R3R70R5y28:flixel%2Fsounds%2Fflixel.mp3R72aR88y28:flixel%2Fsounds%2Fflixel.ogghR6tgoR2i5794R3R73R5R87R72aR86R87hgoR2i33629R3R73R5R89R72aR88R89hgoR2i15744R3R8R9y35:__ASSET__flixel_fonts_nokiafc22_ttfR5y30:flixel%2Ffonts%2Fnokiafc22.ttfR6tgoR2i29724R3R8R9y36:__ASSET__flixel_fonts_monsterrat_ttfR5y31:flixel%2Ffonts%2Fmonsterrat.ttfR6tgoR0y33:flixel%2Fimages%2Fui%2Fbutton.pngR2i519R3R25R5R94R6tgoR0y36:flixel%2Fimages%2Flogo%2Fdefault.pngR2i3280R3R25R5R95R6tgh","rootPath":null,"version":2,"libraryArgs":[],"libraryType":null}